stcloud/__init__.py
stcloud/api_client.py
stcloud/configuration.py
stcloud/rest.py
stcloud/api/__init__.py
stcloud/api/alert_notifications_api.py
stcloud/api/alerts_api.py
stcloud/api/apps_api.py
stcloud/api/aws_settings_controller_api.py
stcloud/api/billing_api.py
stcloud/api/logs_app_api.py
stcloud/api/logs_usage_api_controller_api.py
stcloud/api/monitoring_app_api.py
stcloud/api/reset_password_api.py
stcloud/api/subscriptions_api.py
stcloud/api/tag_api_controller_api.py
stcloud/api/tokens_api_controller_api.py
stcloud/models/__init__.py
stcloud/models/alert_notification.py
stcloud/models/alert_notification_request.py
stcloud/models/alert_rule.py
stcloud/models/alert_rule_response.py
stcloud/models/alert_rule_response_entry.py
stcloud/models/alert_rule_schedule_time_range_dto.py
stcloud/models/alert_rule_schedule_weekday_dto.py
stcloud/models/alert_rules_response.py
stcloud/models/alert_rules_response_entry.py
stcloud/models/app.py
stcloud/models/app_description.py
stcloud/models/app_metadata.py
stcloud/models/app_response.py
stcloud/models/app_response_entry.py
stcloud/models/app_types_response.py
stcloud/models/app_types_response_entry.py
stcloud/models/apps_response.py
stcloud/models/apps_response_entry.py
stcloud/models/basic_auth_method_dto.py
stcloud/models/basic_organization_dto.py
stcloud/models/billing_info.py
stcloud/models/charges_details_response_dto.py
stcloud/models/cloud_watch_settings.py
stcloud/models/cloud_watch_settings_response.py
stcloud/models/cloud_watch_settings_response_entry.py
stcloud/models/create_app_info.py
stcloud/models/create_token_dto.py
stcloud/models/daily_dto.py
stcloud/models/day_usage_data.py
stcloud/models/dimension.py
stcloud/models/error.py
stcloud/models/event_dto.py
stcloud/models/filter_value.py
stcloud/models/generic_api_response.py
stcloud/models/generic_map_based_api_response.py
stcloud/models/invitation.py
stcloud/models/invoice.py
stcloud/models/invoice_response.py
stcloud/models/invoice_response_entry.py
sematext_api_client_python-0.5.0.dist-info/LICENSE
sematext_api_client_python-0.5.0.dist-info/METADATA
sematext_api_client_python-0.5.0.dist-info/WHEEL
sematext_api_client_python-0.5.0.dist-info/top_level.txt
sematext_api_client_python-0.5.0.dist-info/RECORD
