Metadata-Version: 2.1
Name: sematext-api-client-python
Version: 0.5.0
Summary: Sematext Cloud API
Home-page: https://github.com/sematext/sematext-api-client-python
Author-email: 
License: UNKNOWN
Keywords: Sematext,Cloud,API,Monitoring,Logging,Metrics
Platform: UNKNOWN
Classifier: Programming Language :: Python :: 3
Classifier: License :: OSI Approved :: Apache Software License
Classifier: Operating System :: OS Independent
License-File: LICENSE
Requires-Dist: urllib3 (>=1.15)
Requires-Dist: six (>=1.10)
Requires-Dist: certifi
Requires-Dist: python-dateutil
